flask_cdc/cdc.py
flask_cdc_devlibx-0.0.11.dist-info/LICENSE
flask_cdc_devlibx-0.0.11.dist-info/METADATA
flask_cdc_devlibx-0.0.11.dist-info/WHEEL
flask_cdc_devlibx-0.0.11.dist-info/top_level.txt
flask_cdc_devlibx-0.0.11.dist-info/RECORD
