Metadata-Version: 2.1
Name: flask-cdc-devlibx
Version: 0.0.11
Summary: Python DSL for setting up Flask app CDC
Home-page: https://github.com/devlibx/flask-cdc
Author: devlibx
Author-email: devlibxgithub@gmail.com
License: MIT
License-File: LICENSE
Requires-Dist: kafka-python
